nautobot_data_validation_engine/__init__.py
nautobot_data_validation_engine/api/__init__.py
nautobot_data_validation_engine/api/serializers.py
nautobot_data_validation_engine/api/urls.py
nautobot_data_validation_engine/api/views.py
nautobot_data_validation_engine/app-config-schema.json
nautobot_data_validation_engine/custom_validators.py
nautobot_data_validation_engine/datasources.py
nautobot_data_validation_engine/filters.py
nautobot_data_validation_engine/forms.py
nautobot_data_validation_engine/jobs.py
nautobot_data_validation_engine/migrations/0001_initial.py
nautobot_data_validation_engine/migrations/0002_required_unique_types_regex_context.py
nautobot_data_validation_engine/migrations/0003_datacompliance.py
nautobot_data_validation_engine/migrations/0004_created_datetime.py
nautobot_data_validation_engine/migrations/0005_remove_slugs_alter_tags.py
nautobot_data_validation_engine/migrations/0006_add_field_defaults.py
nautobot_data_validation_engine/migrations/0007_alter_datacompliance_compliance_class_name_and_more.py
nautobot_data_validation_engine/migrations/__init__.py
nautobot_data_validation_engine/models.py
nautobot_data_validation_engine/navigation.py
nautobot_data_validation_engine/static/nautobot_data_validation_engine/docs/404.html
nautobot_data_validation_engine/static/nautobot_data_validation_engine/docs/admin/compatibility_matrix.html
nautobot_data_validation_engine/static/nautobot_data_validation_engine/docs/admin/install.html
nautobot_data_validation_engine/static/nautobot_data_validation_engine/docs/admin/release_notes/index.html
nautobot_data_validation_engine/static/nautobot_data_validation_engine/docs/admin/release_notes/version_1.0.html
nautobot_data_validation_engine/static/nautobot_data_validation_engine/docs/admin/release_notes/version_2.0.html
nautobot_data_validation_engine/static/nautobot_data_validation_engine/docs/admin/release_notes/version_2.1.html
nautobot_data_validation_engine-3.4.0.dist-info/LICENSE
nautobot_data_validation_engine-3.4.0.dist-info/METADATA
nautobot_data_validation_engine-3.4.0.dist-info/WHEEL
nautobot_data_validation_engine-3.4.0.dist-info/RECORD
