Metadata-Version: 2.3
Name: nautobot-data-validation-engine
Version: 3.4.0
Summary: Provides UI to build custom data validation rules for data in Nautobot
License: Apache-2.0
Keywords: nautobot,nautobot-app,nautobot-plugin
Author: Network to Code, LLC
Author-email: info@networktocode.com
Requires-Python: >=3.10,<3.13
Classifier: Development Status :: 5 - Production/Stable
Classifier: Intended Audience :: Developers
Classifier: License :: OSI Approved :: Apache Software License
Classifier: Programming Language :: Python :: 3
Classifier: Programming Language :: Python :: 3.10
Classifier: Programming Language :: Python :: 3.11
Classifier: Programming Language :: Python :: 3.12
Provides-Extra: all
Requires-Dist: nautobot (>=2.4.20,<3.0.0)
Project-URL: Documentation, https://docs.nautobot.com/projects/data-validation/en/latest/
Project-URL: Homepage, https://github.com/nautobot/nautobot-app-data-validation-engine
Project-URL: Repository, https://github.com/nautobot/nautobot-app-data-validation-engine
